pwf/__init__.py
pwf/app.py
pwf/cookies.py
pwf/exceptions.py
pwf/helpers.py
pwf/request.py
pwf/response.py
pwf/stack.py
pwf/utils.py
pwf/wrappers.py
pwf-0.2.0.dist-info/DESCRIPTION.rst
pwf-0.2.0.dist-info/METADATA
pwf-0.2.0.dist-info/RECORD
pwf-0.2.0.dist-info/WHEEL
pwf-0.2.0.dist-info/entry_points.txt
pwf-0.2.0.dist-info/metadata.json
pwf-0.2.0.dist-info/top_level.txt
