Metadata-Version: 2.0
Name: pwf
Version: 0.2.0
Summary: A Python Web Framework
Home-page: https://github.com/victorkohler/pwf
Author: Victor Kohler
Author-email: victor@houseofradon.com
License: MIT
Keywords: pwf framework web development
Platform: UNKNOWN
Classifier: Development Status :: 3 - Alpha
Classifier: Intended Audience :: Developers
Classifier: License :: OSI Approved :: MIT License
Classifier: Programming Language :: Python :: 2.7
